README.txt
setup.py
start-tgquotes.py
tgquotes/__init__.py
tgquotes/controllers.py
tgquotes/json.py
tgquotes/model.py
tgquotes/release.py
tgquotes.egg-info/PKG-INFO
tgquotes.egg-info/SOURCES.txt
tgquotes.egg-info/dependency_links.txt
tgquotes.egg-info/not-zip-safe
tgquotes.egg-info/paster_plugins.txt
tgquotes.egg-info/requires.txt
tgquotes.egg-info/sqlobject.txt
tgquotes.egg-info/top_level.txt
tgquotes/config/__init__.py
tgquotes/templates/__init__.py
tgquotes/tests/__init__.py
tgquotes/tests/test_controllers.py
tgquotes/tests/test_model.py
