Metadata-Version: 1.0
Name: tgquotes
Version: 1.0
Summary: A Simple, Embeddable random quote mini-application
Home-page: UNKNOWN
Author: Adam Jones
Author-email: ajones1@gmail.com
License: MIT
Keywords: turbogears.app
Platform: UNKNOWN
Classifier: Development Status :: 3 - Alpha
Classifier: Operating System :: OS Independent
Classifier: Programming Language :: Python
Classifier: Topic :: Software Development :: Libraries :: Python Modules
Classifier: Framework :: TurboGears
